{
  "config": {
    "gdelt_enabled": false,
    "sec_enabled": false,
    "earnings_enabled": false,
    "macro_enabled": false
  },
  "gdelt": {
    "source": "gdelt_connector",
    "enabled": true,
    "mode": "real_connector_stub",
    "reason": "HTTP_QUERY_NOT_IMPLEMENTED",
    "sample_items": [
      {
        "headline": "Geo connector ready",
        "kind": "geo"
      }
    ]
  },
  "sec": {
    "source": "sec_connector",
    "enabled": true,
    "mode": "real_connector_stub",
    "reason": "HTTP_QUERY_NOT_IMPLEMENTED",
    "sample_items": [
      {
        "headline": "SEC connector ready",
        "kind": "corporate"
      }
    ]
  },
  "earnings": {
    "source": "earnings_connector",
    "enabled": true,
    "mode": "real_connector_stub",
    "reason": "HTTP_QUERY_NOT_IMPLEMENTED",
    "sample_items": [
      {
        "headline": "Earnings connector ready",
        "kind": "earnings"
      }
    ]
  },
  "macro": {
    "source": "macro_connector",
    "enabled": true,
    "mode": "real_connector_stub",
    "reason": "HTTP_QUERY_NOT_IMPLEMENTED",
    "sample_items": [
      {
        "headline": "Macro connector ready",
        "kind": "macro"
      }
    ]
  }
}