{
  "symbol": "TSM",
  "name": "Taiwan Semiconductor ADR",
  "themes": [
    "ai",
    "foundry",
    "semis"
  ],
  "sector_hints": [
    "technologie / AI",
    "polovodiče"
  ],
  "business_model": "Dossier pro TSM; doplň dlouhodobou investiční tezi a hlavní zdroje hodnoty.",
  "key_catalysts": [
    "výsledky",
    "guidance",
    "sektorový sentiment"
  ],
  "key_risks": [
    "cykličnost poptávky",
    "capex a supply chain"
  ],
  "watch_for": [
    "silný pohyb ceny s více zdroji",
    "změna guidance nebo regulatoriky"
  ],
  "thesis": "Neutrální výchozí teze – čeká na další upřesnění z research vrstvy.",
  "latest_observations": [],
  "last_updated": "2026-03-26T14:59:45.436547+00:00"
}